zcbe/__init__.py
zcbe/__main__.py
zcbe/build.py
zcbe/dep_manager.py
zcbe/env.py
zcbe/exceptions.py
zcbe/project.py
zcbe/warner.py
zcbe/zcbe.py
zcbe-0.5.1.dist-info/licenses/LICENSE
zcbe-0.5.1.dist-info/METADATA
zcbe-0.5.1.dist-info/WHEEL
zcbe-0.5.1.dist-info/entry_points.txt
zcbe-0.5.1.dist-info/top_level.txt
zcbe-0.5.1.dist-info/RECORD
