Metadata-Version: 2.4
Name: zcbe
Version: 0.5.1
Summary: The Z Cross Build Environment
Home-page: https://github.com/myzhang1029/zcbe
Author: Zhang Maiyun
Author-email: me@maiyun.me
Classifier: Development Status :: 4 - Beta
Classifier: Environment :: Console
Classifier: Intended Audience :: Information Technology
Classifier: License :: OSI Approved :: Apache Software License
Classifier: Operating System :: OS Independent
Classifier: Programming Language :: Python :: 3
Requires-Python: >=3.7
License-File: LICENSE
Requires-Dist: toml
Requires-Dist: typing_extensions; python_version < "3.8"
Dynamic: author
Dynamic: author-email
Dynamic: classifier
Dynamic: description
Dynamic: description-content-type
Dynamic: home-page
Dynamic: license-file
Dynamic: provides-extra
Dynamic: requires-dist
Dynamic: requires-python
Dynamic: summary
